{
  "todos": [
    {
      "id": 1,
      "title": "dasdaqweqweqwesd"
    },
    {
      "title": "ㄴㄴㄴㄴㄴㅁㅁㅁ",
      "id": 15
    },
    {
      "title": "dd",
      "id": 16
    },
    {
      "title": "d",
      "id": 17
    },
    {
      "title": "d",
      "id": 18
    },
    {
      "title": "d",
      "id": 19
    },
    {
      "title": "d",
      "id": 20
    },
    {
      "title": "d",
      "id": 21
    },
    {
      "title": "d",
      "id": 22
    },
    {
      "title": "d",
      "id": 23
    },
    {
      "title": "d",
      "id": 24
    },
    {
      "title": "d",
      "id": 25
    }
  ]
}